{"cameraMode":{"drawMode":0,"name":"Shaded","section":"Shading Mode"},"sceneLighting":true,"audioPlay":false,"sceneViewState":{"showFog":true,"showMaterialUpdate":false,"showSkybox":true,"showFlares":true,"showImageEffects":true,"showParticleSystems":true},"in2DMode":false,"pivot":{"x":-1.8002569675445557,"y":-3.490929365158081,"z":-62.94261169433594},"rotation":{"x":-0.012072455137968064,"y":-0.8436259031295776,"z":-0.018984634429216386,"w":0.5364598631858826},"size":5.870491981506348,"orthographic":false}